drawio_exporter/__init__.py
drawio_exporter/cli.py
drawio_exporter/utils.py
drawio_cli_exporter-0.1.0.dist-info/METADATA
drawio_cli_exporter-0.1.0.dist-info/WHEEL
drawio_cli_exporter-0.1.0.dist-info/entry_points.txt
drawio_cli_exporter-0.1.0.dist-info/RECORD
